coko/__init__.py
coko/__main__.py
coko/launcher.py
coko/classes/__init__.py
coko/classes/configuration.py
coko/classes/console_parser.py
coko/classes/exceptions.py
coko/classes/sync.py
coko/classes/system.py
coko-1.0.17.data/data/share/man/man1/coko.1
coko-1.0.17.dist-info/LICENSE
coko-1.0.17.dist-info/METADATA
coko-1.0.17.dist-info/WHEEL
coko-1.0.17.dist-info/entry_points.txt
coko-1.0.17.dist-info/top_level.txt
coko-1.0.17.dist-info/RECORD
