Metadata-Version: 2.1
Name: coko
Version: 1.0.17
Summary: This tools let you take an snapshot of your files metadata in a particular directory in order to restore those metadata after files have been restored.
Home-page: https://github.com/dante-signal31/coko
Author: Dante Signal31
Author-email: dante.signal31@gmail.com
License: BSD-3
Download-URL: https://github.com/dante-signal31/coko/releases
Keywords: copy over keeping ownership
Platform: UNKNOWN
Classifier: Development Status :: 4 - Beta
Classifier: Intended Audience :: Developers
Classifier: Intended Audience :: Information Technology
Classifier: Intended Audience :: Science/Research
Classifier: Intended Audience :: System Administrators
Classifier: Intended Audience :: Telecommunications Industry
Classifier: Intended Audience :: Other Audience
Classifier: Topic :: System
Classifier: Topic :: Security
Classifier: License :: OSI Approved :: BSD License
Classifier: Operating System :: POSIX :: Linux
Classifier: Programming Language :: Python :: 3
Classifier: Programming Language :: Python :: 3.7
